flowsets/__init__.py
flowsets/flowsets.py
flowsets-0.0.11.dist-info/METADATA
flowsets-0.0.11.dist-info/WHEEL
flowsets-0.0.11.dist-info/RECORD
