Metadata-Version: 2.4
Name: flowsets
Version: 0.0.11
Summary: Flowsets is a revolutionary way to analyse and visualize time-dependent data using fuzzy sets.
Project-URL: Homepage, https://github.com/mjoppich/flowsets
Project-URL: Issues, https://github.com/mjoppich/flowsets/issues
Author-email: Felix Offensperger <offensperger@bio.ifi.lmu.de>, Markus Joppich <joppich@lmu.de>
License-Expression: MIT
Classifier: Intended Audience :: Science/Research
Classifier: Operating System :: OS Independent
Classifier: Programming Language :: Python :: 3
Classifier: Topic :: Scientific/Engineering :: Bio-Informatics
Classifier: Topic :: Scientific/Engineering :: Visualization
Requires-Python: >=3.12
Requires-Dist: matplotlib~=3.10.0
Requires-Dist: natsort~=8.4.0
Requires-Dist: networkx~=3.4.2
Requires-Dist: numpy~=2.2.1
Requires-Dist: pandas~=2.2.3
Requires-Dist: polars~=1.19.0
Requires-Dist: progressbar~=2.5
Requires-Dist: pyarrow~=19.0.0
Requires-Dist: scikit-fuzzy~=0.5.0
Requires-Dist: scikit-learn~=1.6.1
Requires-Dist: scipy~=1.15.1
Requires-Dist: seaborn~=0.13.2
Requires-Dist: six~=1.16.0
Requires-Dist: statsmodels~=0.14.4
